ormedian_utils/__init__.py
ormedian_utils/logger_config.py
ormedian_utils/move_spec_files.py
ormedian_utils/resize_folders.py
ormedian_utils/resize_imgs.py
ormedian_utils/save_frames.py
ormedian_utils/video_folder.py
ormedian_utils-0.2.2.dist-info/METADATA
ormedian_utils-0.2.2.dist-info/WHEEL
ormedian_utils-0.2.2.dist-info/licenses/LICENSE
ormedian_utils-0.2.2.dist-info/RECORD
