Metadata-Version: 2.1
Name: ormedian_utils
Version: 0.2.2
Summary: Utilities for Computer Vision Tasks
Project-URL: Homepage, https://github.com/exponentialR/ormedian-utils
Project-URL: Bug Tracker, https://github.com/exponentialR/ormedian-utils/issues
Author-email: Samuel Adebayo <samueladebayo@ieee.org>
License: AIN'T NO LICENSE BRUV!
License-File: LICENSE
Classifier: License :: OSI Approved :: MIT License
Classifier: Operating System :: OS Independent
Classifier: Programming Language :: Python :: 3
Requires-Python: >=3.6
Requires-Dist: colorama
Requires-Dist: opencv-python>=4.5.5.62
Requires-Dist: pillow
Requires-Dist: tqdm
